Metadata-Version: 2.4
Name: adafruit-circuitpython-il0398
Version: 2.0.3
Summary: CircuitPython displayio drivers for IL0398 driven e-paper displays
Author-email: Adafruit Industries <circuitpython@adafruit.com>
License: MIT
Project-URL: Homepage, https://github.com/adafruit/Adafruit_CircuitPython_IL0398
Keywords: adafruit,blinka,circuitpython,micropython,il0398,displayio,e-paper,display
Classifier: Intended Audience :: Developers
Classifier: Topic :: Software Development :: Libraries
Classifier: Topic :: Software Development :: Embedded Systems
Classifier: Topic :: System :: Hardware
Classifier: License :: OSI Approved :: MIT License
Classifier: Programming Language :: Python :: 3
License-File: LICENSE
Requires-Dist: Adafruit-Blinka
Provides-Extra: optional
Dynamic: license-file
